{"cameraMode":{"drawMode":0,"name":"Shaded","section":"Shading Mode"},"sceneLighting":true,"audioPlay":false,"sceneViewState":{"showFog":true,"showMaterialUpdate":false,"showSkybox":true,"showFlares":true,"showImageEffects":true,"showParticleSystems":true},"in2DMode":false,"pivot":{"x":136.21115112304688,"y":-121.40579223632813,"z":-264.1051025390625},"rotation":{"x":-0.08889807760715485,"y":0.8736256957054138,"z":-0.44647976756095889,"w":-0.17347359657287599},"size":96.75765228271485,"orthographic":false}